edacious/__init__.py
edacious/redis.py
edacious/sqs.py
edacious-0.0.11.dist-info/METADATA
edacious-0.0.11.dist-info/WHEEL
edacious-0.0.11.dist-info/top_level.txt
edacious-0.0.11.dist-info/RECORD
