Metadata-Version: 2.1
Name: edacious
Version: 0.0.11
Summary: Edacious an Event Derive Architecture framework
Home-page: https://github.com/eldad1221/edacious
Author: Eldad Bishari
Author-email: eldad@1221tlv.org
Classifier: Programming Language :: Python :: 3
Classifier: License :: OSI Approved :: MIT License
Classifier: Operating System :: OS Independent
Requires-Python: >=3.8
Requires-Dist: quickbelog >=1.1.0
Requires-Dist: flask >=2.0.0
